cordic_verilog.v
`timescale 1ns/1ps

// ===========================================================
// CORDIC (Rotation Mode) - 2.16 Fixed-Point Implementation
// Computes cosine and sine using iterative shifts and adds
// ===========================================================

module cordic (
    input wire clk,                           // Clock
    input wire rst,                           // Reset
    input wire signed [17:0] angle_in,        // Input angle in 2.16 format (radians)
    input wire start,                         // Start signal to begin computation
    output reg signed [17:0] cos_out,         // Output cosine value (2.16 fixed-point)
    output reg signed [17:0] sin_out,         // Output sine value (2.16 fixed-point)
    output reg done                           // Done flag to indicate completion
);

    // Number of CORDIC iterations (precision limited to 14)
    parameter ITERATIONS = 14;

    // Scaling constant (K ≈ 0.60725 * 65536 ≈ 39849 in 2.16 fixed-point)
    parameter signed [17:0] K = 18'd39849;

    // Lookup table of arctangent values in 2.16 fixed-point
    reg signed [17:0] atan_table [0:15];
    initial begin
        atan_table[0]  = 18'd51471;  // atan(2^0)   ≈ 45°
        atan_table[1]  = 18'd30385;  // atan(2^-1)  ≈ 26.565°
        atan_table[2]  = 18'd16054;  // atan(2^-2)
        atan_table[3]  = 18'd8145;
        atan_table[4]  = 18'd4090;
        atan_table[5]  = 18'd2045;
        atan_table[6]  = 18'd1023;
        atan_table[7]  = 18'd512;
        atan_table[8]  = 18'd256;
        atan_table[9]  = 18'd128;
        atan_table[10] = 18'd64;
        atan_table[11] = 18'd32;
        atan_table[12] = 18'd16;
        atan_table[13] = 18'd8;
        atan_table[14] = 18'd4;
        atan_table[15] = 18'd2;
    end

    // Internal registers
    reg signed [17:0] x, y, z;    // x = cos, y = sin, z = angle accumulator
    reg [4:0] i;                  // Iteration counter (5 bits for up to 32)
    reg running;                 // Active flag

    always @(posedge clk or posedge rst) begin
        if (rst) begin
            // Reset all values
            cos_out <= 0;
            sin_out <= 0;
            done <= 0;
            running <= 0;
        end else begin
            if (start && !running) begin
                // Begin CORDIC operation
                x <= K;          // Start with scaling factor
                y <= 0;          // y starts at 0
                z <= angle_in;   // Input angle loaded into accumulator
                i <= 0;          // Reset iteration counter
                running <= 1;    // Mark as running
                done <= 0;
                $display("=== CORDIC Start ===");
                $display("Input angle (fixed) = %d", angle_in);
            end else if (running) begin
                // Perform one iteration of CORDIC
                if (i < ITERATIONS) begin
                    if (z >= 0) begin
                        // Rotate clockwise
                        x <= x - (y >>> i);
                        y <= y + (x >>> i);
                        z <= z - atan_table[i];
                    end else begin
                        // Rotate counterclockwise
                        x <= x + (y >>> i);
                        y <= y - (x >>> i);
                        z <= z + atan_table[i];
                    end

                    // Debug output per iteration
                    $display("iter=%0d | A=%0d | x=%0d | y=%0d", i, z, x, y);
                    i <= i + 1;
                end else begin
                    // All iterations done, output result
                    cos_out <= x;
                    sin_out <= y;
                    done <= 1;
                    running <= 0;
                    $display("=== CORDIC Done ===");
                    $display("Final Cos = %d, Sin = %d", x, y);
                end
            end
        end
    end

endmodule

testbench_verilog.v
`timescale 1ns/1ps

// ===========================================================
// Testbench for the CORDIC sine and cosine processor
// Simulates angles from -π/2 to +π/2 in 2.16 fixed-point
// format and compares results against expected math values.
// Also records waveforms for GTKWave viewing.
// ===========================================================

module cordic_tb;

    // -------------------------------
    // Inputs to the CORDIC module
    // -------------------------------
    reg clk = 0;                     // Clock signal
    reg rst = 0;                     // Reset signal
    reg start = 0;                   // Start signal to begin CORDIC operation
    reg signed [17:0] angle_in;      // Input angle in 2.16 fixed-point format (signed)

    // -------------------------------
    // Outputs from the CORDIC module
    // -------------------------------
    wire signed [17:0] cos_out;      // Output cosine value in 2.16 format
    wire signed [17:0] sin_out;      // Output sine value in 2.16 format
    wire done;                       // Signal that goes high when calculation is complete

    // Instantiate the CORDIC Unit Under Test (UUT)
    cordic uut (
        .clk(clk),
        .rst(rst),
        .angle_in(angle_in),
        .start(start),
        .cos_out(cos_out),
        .sin_out(sin_out),
        .done(done)
    );

    // Clock signal toggles every 5 ns (10 ns period)
    always #5 clk = ~clk;

    // -------------------------------
    // For comparison and evaluation
    // -------------------------------
    reg signed [17:0] expected_cos;  // Expected cosine value (computed using $cos())
    reg signed [17:0] expected_sin;  // Expected sine value (computed using $sin())
    reg [4:0] cos_match, sin_match;  // Number of leading matching bits

    // Function to count how many leading bits match
    function [4:0] count_leading_match;
        input [17:0] a, b;
        integer j;
        begin : compare_loop
            count_leading_match = 0;
            for (j = 17; j >= 0; j = j - 1) begin
                if (a[j] == b[j])
                    count_leading_match = count_leading_match + 1; // Bits match
                else
                    disable compare_loop; // Stop comparing once a bit differs
            end
        end
    endfunction

    // Real number representations for math comparison
    real rad;                // Real angle in radians
    real cos_real, sin_real; // Cosine and sine calculated with $cos() and $sin()

    // Variables for looping
    integer angle_fp;        // Angle in fixed-point to sweep through test cases
    integer step;            // Step size between test angles

    initial begin
        // -------------------------------
        // Waveform file generation setup
        // -------------------------------
        $dumpfile("cordic.vcd");       // File for GTKWave viewing
        $dumpvars(0, cordic_tb);       // Dump all signals in the testbench

        // Print table header to terminal
        $display("Angle (2.16) | Cos (Out) | Cos (Exp) | CosMatch | Sin (Out) | Sin (Exp) | SinMatch");

        // Apply reset at start
        rst = 1; #10 rst = 0;

        // Set step size for sweeping input angles (~1 degree steps)
        step = 1029;

        // Sweep input angles from -π/2 to +π/2
        for (angle_fp = -102944; angle_fp <= 102944; angle_fp = angle_fp + step) begin
            angle_in = angle_fp;  // Set input angle

            // Convert angle from fixed-point to real radians
            rad = angle_fp / 65536.0;

            // Compute expected values using built-in math functions
            cos_real = $cos(rad);
            sin_real = $sin(rad);

            // Convert expected values to fixed-point format
            expected_cos = $rtoi(cos_real * 65536.0);
            expected_sin = $rtoi(sin_real * 65536.0);

            // Trigger CORDIC calculation
            start = 1; #10 start = 0;  // Start pulse
            wait (done);              // Wait until done signal is high
            #5;                       // Delay to stabilize output

            // Compare outputs to expected and calculate matching bits
            cos_match = count_leading_match(cos_out, expected_cos);
            sin_match = count_leading_match(sin_out, expected_sin);

            // Print results to terminal
            $display("%d | %d | %d | %0d | %d | %d | %0d",
                     angle_in, cos_out, expected_cos, cos_match,
                     sin_out, expected_sin, sin_match);
        end

        $finish;  // End of simulation
    end

endmodule

cordic.vcd
$date
	Mon Apr 14 22:06:56 2025
$end
$version
	Icarus Verilog
$end
$timescale
	1ps
$end
$scope module cordic_tb $end
$var wire 18 ! sin_out [17:0] $end
$var wire 1 " done $end
$var wire 18 # cos_out [17:0] $end
$var reg 18 $ angle_in [17:0] $end
$var reg 1 % clk $end
$var reg 5 & cos_match [4:0] $end
$var reg 18 ' expected_cos [17:0] $end
$var reg 18 ( expected_sin [17:0] $end
$var reg 1 ) rst $end
$var reg 5 * sin_match [4:0] $end
$var reg 1 + start $end
$var integer 32 , angle_fp [31:0] $end
$var real 1 - cos_real $end
$var real 1 . rad $end
$var real 1 / sin_real $end
$var integer 32 0 step [31:0] $end
$scope function count_leading_match $end
$var reg 18 1 a [17:0] $end
$var reg 18 2 b [17:0] $end
$var integer 32 3 j [31:0] $end
$scope begin compare_loop $end
$upscope $end
$upscope $end
$scope module uut $end
$var wire 18 4 angle_in [17:0] $end
$var wire 1 % clk $end
$var wire 1 ) rst $end
$var wire 1 + start $end
$var reg 18 5 cos_out [17:0] $end
$var reg 1 " done $end
$var reg 5 6 i [4:0] $end
$var reg 1 7 running $end
$var reg 18 8 sin_out [17:0] $end
$var reg 18 9 x [17:0] $end
$var reg 18 : y [17:0] $end
$var reg 18 ; z [17:0] $end
$upscope $end
$upscope $end
$enddefinitions $end
#0
$dumpvars
bx ;
bx :
bx 9
b0 8
07
bx 6
b0 5
bx 4
bx 3
bx 2
bx 1
bx 0
r0 /
r0 .
r0 -
bx ,
0+
bx *
1)
bx (
bx '
bx &
0%
bx $
b0 #
0"
b0 !
$end
#5000
1%
#10000
0%
1+
b110000000000000001 (
b0 '
r-0.9999999999900789 /
r-4.454455103366037e-06 -
r-1.57080078125 .
b100110110111100000 $
b100110110111100000 4
b11111111111111100110110111100000 ,
b10000000101 0
0)
#15000
17
b0 6
b100110110111100000 ;
b0 :
b1001101110101001 9
1%
#20000
0%
0+
#25000
b1 6
b110011011011101111 ;
b110110010001010111 :
1%
#30000
0%
#35000
b10 6
b111010110110100000 ;
b110001011010000011 :
b100110111010100 9
1%
#40000
0%
#45000
b11 6
b111110110001010110 ;
b110000001100001110 :
b1001101110100 9
1%
#50000
0%
#55000
b100 6
b110000100111 ;
b110000000010100000 :
b111111001111010101 9
1%
#60000
0%
#65000
b101 6
b111111110000101101 ;
b101111111111011101 :
b1111001011 9
1%
#70000
0%
#75000
b110 6
b10000101010 ;
b101111111110111111 :
b111111101111001001 9
1%
#80000
0%
#85000
b111 6
b101011 ;
b101111111110101110 :
b111111111111001011 9
1%
#90000
0%
#95000
b1000 6
b111111111000101011 ;
b101111111110101101 :
b111001100 9
1%
#100000
0%
#105000
b1001 6
b111111111100101011 ;
b101111111110101100 :
b11001011 9
1%
#110000
0%
#115000
b1010 6
b111111111110101011 ;
b1001010 9
1%
#120000
0%
#125000
b1011 6
b111111111111101011 ;
b1001 9
1%
#130000
0%
#135000
b1100 6
b1011 ;
b111111111111101000 9
1%
#140000
0%
#145000
b1101 6
b111111111111111011 ;
b101111111110101011 :
b111111111111111001 9
1%
#150000
0%
#155000
b1110 6
b11 ;
b101111111110101100 :
b111111111111110000 9
1%
#160000
0%
#165000
07
1"
b101111111110101100 !
b101111111110101100 8
b111111111111110000 #
b111111111111110000 5
1%
#170000
1+
b110000000000001001 (
b10000000100 '
r-0.9998768071445057 /
r0.01569619490542211 -
r-1.555099487304688 .
b100111000111100101 $
b100111000111100101 4
b11111111111111100111000111100101 ,
b1 *
b0 &
b10000 3
b101111111110101100 1
b110000000000000001 2
0%
#175000
0"
17
b0 6
b100111000111100101 ;
b0 :
b1001101110101001 9
1%
#180000
0%
0+
#185000
b1 6
b110011101011110100 ;
b110110010001010111 :
1%
#190000
0%
#195000
b10 6
b111011000110100101 ;
b110001011010000011 :
b100110111010100 9
1%
#200000
0%
#205000
b11 6
b111111000001011011 ;
b110000001100001110 :
b1001101110100 9
1%
#210000
0%
#215000
b100 6
b1000000101100 ;
b110000000010100000 :
b111111001111010101 9
1%
#220000
0%
#225000
b101 6
b110010 ;
b101111111111011101 :
b1111001011 9
1%
#230000
0%
#235000
b110 6
b111111100000110101 ;
b101111111111111011 :
b101111001101 9
1%
#240000
0%
#245000
b111 6
b111111110000110100 ;
b101111111111001100 :
b11111001100 9
1%
#250000
0%
#255000
b1000 6
b111111111000110100 ;
b101111111110111101 :
b10111001011 9
1%
#260000
0%
#265000
b1001 6
b111111111100110100 ;
b101111111110111000 :
b10011001010 9
1%
#270000
0%
#275000
b1010 6
b111111111110110100 ;
b101111111110110110 :
b10001001001 9
1%
#280000
0%
#285000
b1011 6
b111111111111110100 ;
b101111111110110101 :
b10000001000 9
1%
#290000
0%
#295000
b1100 6
b10100 ;
b1111100111 9
1%
#300000
0%
#305000
b1101 6
b100 ;
b1111111000 9
1%
#310000
0%
#315000
b1110 6
b111111111111111100 ;
b10000000001 9
1%
#320000
0%
#325000
07
1"
b101111111110110101 !
b101111111110110101 8
b10000000001 #
b10000000001 5
1%
#330000
1+
b110000000000100001 (
b100000001001 '
r-0.9995071191023016 /
r0.03139297475260162 -
r-1.539398193359375 .
b100111010111101010 $
b100111010111101010 4
b11111111111111100111010111101010 ,
b1111 &
b10000 3
b101111111110110101 1
b110000000000001001 2
0%
#335000
0"
17
b0 6
b100111010111101010 ;
b0 :
b1001101110101001 9
1%
#340000
0%
0+
#345000
b1 6
b110011111011111001 ;
b110110010001010111 :
1%
#350000
0%
#355000
b10 6
b111011010110101010 ;
b110001011010000011 :
b100110111010100 9
1%
#360000
0%
#365000
b11 6
b111111010001100000 ;
b110000001100001110 :
b1001101110100 9
1%
#370000
0%
#375000
b100 6
b1010000110001 ;
b110000000010100000 :
b111111001111010101 9
1%
#380000
0%
#385000
b101 6
b10000110111 ;
b101111111111011101 :
b1111001011 9
1%
#390000
0%
#395000
b110 6
b111111110000111010 ;
b101111111111111011 :
b101111001101 9
1%
#400000
0%
#405000
b111 6
b111001 ;
b101111111111001100 :
b11111001100 9
1%
#410000
0%
#415000
b1000 6
b111111111000111001 ;
b101111111111011011 :
b100111001101 9
1%
#420000
0%
#425000
b1001 6
b111111111100111001 ;
b101111111111010010 :
b100011001100 9
1%
#430000
0%
#435000
b1010 6
b111111111110111001 ;
b101111111111001110 :
b100001001011 9
1%
#440000
0%
#445000
b1011 6
b111111111111111001 ;
b101111111111001100 :
b100000001010 9
1%
#450000
0%
#455000
b1100 6
b11001 ;
b101111111111001011 :
b11111101001 9
1%
#460000
0%
#465000
b1101 6
b1001 ;
b11111111010 9
1%
#470000
0%
#475000
b1110 6
b1 ;
b100000000011 9
1%
#480000
0%
#485000
07
1"
b101111111111001011 !
b101111111111001011 8
b100000000011 #
b100000000011 5
1%
#490000
1+
b110000000001001001 (
b110000001101 '
r-0.9988910270010208 /
r0.04708201542888611 -
r-1.523696899414062 .
b100111100111101111 $
b100111100111101111 4
b11111111111111100111100111101111 ,
b1110 &
b10000 3
b101111111111001011 1
b110000000000100001 2
0%
#495000
0"
17
b0 6
b100111100111101111 ;
b0 :
b1001101110101001 9
1%
#500000
0%
0+
#505000
b1 6
b110100001011111110 ;
b110110010001010111 :
1%
#510000
0%
#515000
b10 6
b111011100110101111 ;
b110001011010000011 :
b100110111010100 9
1%
#520000
0%
#525000
b11 6
b111111100001100101 ;
b110000001100001110 :
b1001101110100 9
1%
#530000
0%
#535000
b100 6
b1100000110110 ;
b110000000010100000 :
b111111001111010101 9
1%
#540000
0%
#545000
b101 6
b100000111100 ;
b101111111111011101 :
b1111001011 9
1%
#550000
0%
#555000
b110 6
b111111 ;
b101111111111111011 :
b101111001101 9
1%
#560000
0%
#565000
b111 6
b111111110001000000 ;
b110000000000101010 :
b111111001110 9
1%
#570000
0%
#575000
b1000 6
b111111111001000000 ;
b110000000000001011 :
b110111001110 9
1%
#580000
0%
#585000
b1001 6
b111111111101000000 ;
b101111111111111110 :
b110011001110 9
1%
#590000
0%
#595000
b1010 6
b111111111111000000 ;
b101111111111111000 :
b110001001101 9
1%
#600000
0%
#605000
b1011 6
b0 ;
b101111111111110101 :
b110000001100 9
1%
#610000
0%
#615000
b1100 6
b111111111111100000 ;
b101111111111110110 :
b110000101101 9
1%
#620000
0%
#625000
b1101 6
b111111111111110000 ;
b110000011100 9
1%
#630000
0%
#635000
b1110 6
b111111111111111000 ;
b110000010011 9
1%
#640000
0%
#645000
07
1"
b101111111111110110 !
b101111111111110110 8
b110000010011 #
b110000010011 5
1%
#650000
1+
b110000000010000010 (
b1000000010001 '
r-0.9980286827231178 /
r0.06275944918462999 -
r-1.50799560546875 .
b100111110111110100 $
b100111110111110100 4
b11111111111111100111110111110100 ,
b1101 &
b10000 3
b101111111111110110 1
b110000000001001001 2
0%
#655000
0"
17
b0 6
b100111110111110100 ;
b0 :
b1001101110101001 9
1%
#660000
0%
0+
#665000
b1 6
b110100011100000011 ;
b110110010001010111 :
1%
#670000
0%
#675000
b10 6
b111011110110110100 ;
b110001011010000011 :
b100110111010100 9
1%
#680000
0%
#685000
b11 6
b111111110001101010 ;
b110000001100001110 :
b1001101110100 9
1%
#690000
0%
#695000
b100 6
b1110000111011 ;
b110000000010100000 :
b111111001111010101 9
1%
#700000
0%
#705000
b101 6
b110001000001 ;
b101111111111011101 :
b1111001011 9
1%
#710000
0%
#715000
b110 6
b10001000100 ;
b101111111111111011 :
b101111001101 9
1%
#720000
0%
#725000
b111 6
b1000101 ;
b110000000000101010 :
b111111001110 9
1%
#730000
0%
#735000
b1000 6
b111111111001000101 ;
b110000000001001001 :
b1000111001110 9
1%
#740000
0%
#745000
b1001 6
b111111111101000101 ;
b110000000000111000 :
b1000011001110 9
1%
#750000
0%
#755000
b1010 6
b111111111111000101 ;
b110000000000110000 :
b1000001001110 9
1%
#760000
0%
#765000
b1011 6
b101 ;
b110000000000101100 :
b1000000001110 9
1%
#770000
0%
#775000
b1100 6
b111111111111100101 ;
b110000000000101110 :
b1000000101110 9
1%
#780000
0%
#785000
b1101 6
b111111111111110101 ;
b110000000000101101 :
b1000000011110 9
1%
#790000
0%
#795000
b1110 6
b111111111111111101 ;
b1000000010110 9
1%
#800000
0%
#805000
07
1"
b110000000000101101 !
b110000000000101101 8
b1000000010110 #
b1000000010110 5
1%
#810000
1+
b110000000011001010 (
b1010000010011 '
r-0.9969202988585045 /
r0.07842141113159035 -
r-1.492294311523438 .
b101000000111111001 $
b101000000111111001 4
b11111111111111101000000111111001 ,
b1010 *
b1111 &
b111 3
b110000000000101101 1
b110000000010000010 2
0%
#815000
0"
17
b0 6
b101000000111111001 ;
b0 :
b1001101110101001 9
1%
#820000
0%
0+
#825000
b1 6
b110100101100001000 ;
b110110010001010111 :
1%
#830000
0%
#835000
b10 6
b111100000110111001 ;
b110001011010000011 :
b100110111010100 9
1%
#840000
0%
#845000
b11 6
b1101111 ;
b110000001100001110 :
b1001101110100 9
1%
#850000
0%
#855000
b100 6
b111110000010011110 ;
b110000010101111100 :
b11001100010011 9
1%
#860000
0%
#865000
b101 6
b111111000010011000 ;
b110000001001001011 :
b10001101101010 9
1%
#870000
0%
#875000
b110 6
b111111100010010101 ;
b110000000100110000 :
b1101101111100 9
1%
#880000
0%
#885000
b111 6
b111111110010010100 ;
b110000000011000011 :
b1011110000000 9
1%
#890000
0%
#895000
b1000 6
b111111111010010100 ;
b110000000010010100 :
b1010110000001 9
1%
#900000
0%
#905000
b1001 6
b111111111110010100 ;
b110000000001111111 :
b1010010000001 9
1%
#910000
0%
#915000
b1010 6
b10100 ;
b110000000001110101 :
b1010000000001 9
1%
#920000
0%
#925000
b1011 6
b111111111111010100 ;
b110000000001111010 :
b1010001000001 9
1%
#930000
0%
#935000
b1100 6
b111111111111110100 ;
b110000000001111000 :
b1010000100001 9
1%
#940000
0%
#945000
b1101 6
b100 ;
b110000000001110111 :
b1010000010001 9
1%
#950000
0%
#955000
b1110 6
b111111111111111100 ;
b1010000011001 9
1%
#960000
0%
#965000
07
1"
b110000000001110111 !
b110000000001110111 8
b1010000011001 #
b1010000011001 5
1%
#970000
1+
b110000000100100011 (
b1100000010100 '
r-0.9955661486521414 /
r0.09406404019572072 -
r-1.476593017578125 .
b101000010111111110 $
b101000010111111110 4
b11111111111111101000010111111110 ,
b1110 &
b111 3
b110000000001110111 1
b110000000011001010 2
0%
#975000
0"
17
b0 6
b101000010111111110 ;
b0 :
b1001101110101001 9
1%
#980000
0%
0+
#985000
b1 6
b110100111100001101 ;
b110110010001010111 :
1%
#990000
0%
#995000
b10 6
b111100010110111110 ;
b110001011010000011 :
b100110111010100 9
1%
#1000000
0%
#1005000
b11 6
b10001110100 ;
b110000001100001110 :
b1001101110100 9
1%
#1010000
0%
#1015000
b100 6
b111110010010100011 ;
b110000010101111100 :
b11001100010011 9
1%
#1020000
0%
#1025000
b101 6
b111111010010011101 ;
b110000001001001011 :
b10001101101010 9
1%
#1030000
0%
#1035000
b110 6
b111111110010011010 ;
b110000000100110000 :
b1101101111100 9
1%
#1040000
0%
#1045000
b111 6
b10011001 ;
b110000000011000011 :
b1011110000000 9
1%
#1050000
0%
#1055000
b1000 6
b111111111010011001 ;
b110000000011110010 :
b1100101111111 9
1%
#1060000
0%
#1065000
b1001 6
b111111111110011001 ;
b110000000011011001 :
b1100001111111 9
1%
#1070000
0%
#1075000
b1010 6
b11001 ;
b110000000011001101 :
b1011111111111 9
1%
#1080000
0%
#1085000
b1011 6
b111111111111011001 ;
b110000000011010010 :
b1100000111111 9
1%
#1090000
0%
#1095000
b1100 6
b111111111111111001 ;
b110000000011001111 :
b1100000011111 9
1%
#1100000
0%
#1105000
b1101 6
b1001 ;
b110000000011001110 :
b1100000001111 9
1%
#1110000
0%
#1115000
b1110 6
b1 ;
b1100000010111 9
1%
#1120000
0%
#1125000
07
1"
b110000000011001110 !
b110000000011001110 8
b1100000010111 #
b1100000010111 5
1%
#1130000
1+
b110000000110001100 (
b1110000010100 '
r-0.9939665659366758 /
r0.1096834800690245 -
r-1.460891723632812 .
b101000101000000011 $
b101000101000000011 4
b11111111111111101000101000000011 ,
b1001 *
b10000 &
b1000 3
b110000000011001110 1
b110000000100100011 2
0%
#1135000
0"
17
b0 6
b101000101000000011 ;
b0 :
b1001101110101001 9
1%
#1140000
0%
0+
#1145000
b1 6
b110101001100010010 ;
b110110010001010111 :
1%
#1150000
0%
#1155000
b10 6
b111100100111000011 ;
b110001011010000011 :
b100110111010100 9
1%
#1160000
0%
#1165000
b11 6
b100001111001 ;
b110000001100001110 :
b1001101110100 9
1%
#1170000
0%
#1175000
b100 6
b111110100010101000 ;
b110000010101111100 :
b11001100010011 9
1%
#1180000
0%
#1185000
b101 6
b111111100010100010 ;
b110000001001001011 :
b10001101101010 9
1%
#1190000
0%
#1195000
b110 6
b10011111 ;
b110000000100110000 :
b1101101111100 9
1%
#1200000
0%
#1205000
b111 6
b111111110010100000 ;
b110000000110011101 :
b1111101111000 9
1%
#1210000
0%
#1215000
b1000 6
b111111111010100000 ;
b110000000101011111 :
b1110101111011 9
1%
#1220000
0%
#1225000
b1001 6
b111111111110100000 ;
b110000000101000010 :
b1110001111100 9
1%
#1230000
0%
#1235000
b1010 6
b100000 ;
b110000000100110100 :
b1101111111100 9
1%
#1240000
0%
#1245000
b1011 6
b111111111111100000 ;
b110000000100111010 :
b1110000111100 9
1%
#1250000
0%
#1255000
b1100 6
b0 ;
b110000000100110111 :
b1110000011100 9
1%
#1260000
0%
#1265000
b1101 6
b111111111111110000 ;
b110000000100111000 :
b1110000101100 9
1%
#1270000
0%
#1275000
b1110 6
b111111111111111000 ;
b1110000100100 9
1%
#1280000
0%
#1285000
07
1"
b110000000100111000 !
b110000000100111000 8
b1110000100100 #
b1110000100100 5
1%
#1290000
1+
b110000001000000101 (
b10000000010010 '
r-0.992121945050143 /
r0.1252758801602336 -
r-1.4451904296875 .
b101000111000001000 $
b101000111000001000 4
b11111111111111101000111000001000 ,
b1010 *
b1100 &
b111 3
b110000000100111000 1
b110000000110001100 2
0%
#1295000
0"
17
b0 6
b101000111000001000 ;
b0 :
b1001101110101001 9
1%
#1300000
0%
0+
#1305000
b1 6
b110101011100010111 ;
b110110010001010111 :
1%
#1310000
0%
#1315000
b10 6
b111100110111001000 ;
b110001011010000011 :
b100110111010100 9
1%
#1320000
0%
#1325000
b11 6
b110001111110 ;
b110000001100001110 :
b1001101110100 9
1%
#1330000
0%
#1335000
b100 6
b111110110010101101 ;
b110000010101111100 :
b11001100010011 9
1%
#1340000
0%
#1345000
b101 6
b111111110010100111 ;
b110000001001001011 :
b10001101101010 9
1%
#1350000
0%
#1355000
b110 6
b10010100100 ;
b110000000100110000 :
b1101101111100 9
1%
#1360000
0%
#1365000
b111 6
b10100101 ;
b110000000110011101 :
b1111101111000 9
1%
#1370000
0%
#1375000
b1000 6
b111111111010100101 ;
b110000000111011011 :
b10000101110101 9
1%
#1380000
0%
#1385000
b1001 6
b111111111110100101 ;
b110000000110111010 :
b10000001110110 9
1%
#1390000
0%
#1395000
b1010 6
b100101 ;
b110000000110101010 :
b1111111110110 9
1%
#1400000
0%
#1405000
b1011 6
b111111111111100101 ;
b110000000110110001 :
b10000000110110 9
1%
#1410000
0%
#1415000
b1100 6
b101 ;
b110000000110101101 :
b10000000010110 9
1%
#1420000
0%
#1425000
b1101 6
b111111111111110101 ;
b110000000110101111 :
b10000000100110 9
1%
#1430000
0%
#1435000
b1110 6
b111111111111111101 ;
b110000000110101110 :
b10000000011110 9
1%
#1440000
0%
#1445000
07
1"
b110000000110101110 !
b110000000110101110 8
b10000000011110 #
b10000000011110 5
1%
#1450000
1+
b110000001010001110 (
b10010000001101 '
r-0.9900327407387527 /
r0.1408373965440774 -
r-1.429489135742188 .
b101001001000001101 $
b101001001000001101 4
b11111111111111101001001000001101 ,
b1000 *
b1110 &
b1001 3
b110000000110101110 1
b110000001000000101 2
0%
#1455000
0"
17
b0 6
b101001001000001101 ;
b0 :
b1001101110101001 9
1%
#1460000
0%
0+
#1465000
b1 6
b110101101100011100 ;
b110110010001010111 :
1%
#1470000
0%
#1475000
b10 6
b111101000111001101 ;
b110001011010000011 :
b100110111010100 9
1%
#1480000
0%
#1485000
b11 6
b1000010000011 ;
b110000001100001110 :
b1001101110100 9
1%
#1490000
0%
#1495000
b100 6
b111111000010110010 ;
b110000010101111100 :
b11001100010011 9
1%
#1500000
0%
#1505000
b101 6
b10101100 ;
b110000001001001011 :
b10001101101010 9
1%
#1510000
0%
#1515000
b110 6
b111111100010101111 ;
b110000001101100110 :
b10101101011000 9
1%
#1520000
0%
#1525000
b111 6
b111111110010101110 ;
b110000001010111001 :
b10011101100101 9
1%
#1530000
0%
#1535000
b1000 6
b111111111010101110 ;
b110000001001101011 :
b10010101101010 9
1%
#1540000
0%
#1545000
b1001 6
b111111111110101110 ;
b110000001001000110 :
b10010001101100 9
1%
#1550000
0%
#1555000
b1010 6
b101110 ;
b110000001000110100 :
b10001111101101 9
1%
#1560000
0%
#1565000
b1011 6
b111111111111101110 ;
b110000001000111100 :
b10010000101101 9
1%
#1570000
0%
#1575000
b1100 6
b1110 ;
b110000001000111000 :
b10010000001101 9
1%
#1580000
0%
#1585000
b1101 6
b111111111111111110 ;
b110000001000111010 :
b10010000011101 9
1%
#1590000
0%
#1595000
b1110 6
b110 ;
b110000001000111001 :
b10010000010101 9
1%
#1600000
0%
#1605000
07
1"
b110000001000111001 !
b110000001000111001 8
b10010000010101 #
b10010000010101 5
1%
#1610000
1+
b110000001100100111 (
b10100000000111 '
r-0.9876994680447821 /
r0.1563641929089087 -
r-1.413787841796875 .
b101001011000010010 $
b101001011000010010 4
b11111111111111101001011000010010 ,
b1010 *
b1101 &
b111 3
b110000001000111001 1
b110000001010001110 2
0%
#1615000
0"
17
b0 6
b101001011000010010 ;
b0 :
b1001101110101001 9
1%
#1620000
0%
0+
#1625000
b1 6
b110101111100100001 ;
b110110010001010111 :
1%
#1630000
0%
#1635000
b10 6
b111101010111010010 ;
b110001011010000011 :
b100110111010100 9
1%
#1640000
0%
#1645000
b11 6
b1010010001000 ;
b110000001100001110 :
b1001101110100 9
1%
#1650000
0%
#1655000
b100 6
b111111010010110111 ;
b110000010101111100 :
b11001100010011 9
1%
#1660000
0%
#1665000
b101 6
b10010110001 ;
b110000001001001011 :
b10001101101010 9
1%
#1670000
0%
#1675000
b110 6
b111111110010110100 ;
b110000001101100110 :
b10101101011000 9
1%
#1680000
0%
#1685000
b111 6
b10110011 ;
b110000001010111001 :
b10011101100101 9
1%
#1690000
0%
#1695000
b1000 6
b111111111010110011 ;
b110000001100000111 :
b10100101100000 9
1%
#1700000
0%
#1705000
b1001 6
b111111111110110011 ;
b110000001011011110 :
b10100001100011 9
1%
#1710000
0%
#1715000
b1010 6
b110011 ;
b110000001011001010 :
b10011111100100 9
1%
#1720000
0%
#1725000
b1011 6
b111111111111110011 ;
b110000001011010011 :
b10100000100100 9
1%
#1730000
0%
#1735000
b1100 6
b10011 ;
b110000001011001110 :
b10100000000100 9
1%
#1740000
0%
#1745000
b1101 6
b11 ;
b110000001011010000 :
b10100000010100 9
1%
#1750000
0%
#1755000
b1110 6
b111111111111111011 ;
b110000001011010001 :
b10100000011100 9
1%
#1760000
0%
#1765000
07
1"
b110000001011010001 !
b110000001011010001 8
b10100000011100 #
b10100000011100 5
1%
#1770000
1+
b110000001111001111 (
b10101111111110 '
r-0.9851227021796046 /
r0.171852441502453 -
r-1.398086547851562 .
b101001101000010111 $
b101001101000010111 4
b11111111111111101001101000010111 ,
b1001 *
b1000 3
b110000001011010001 1
b110000001100100111 2
0%
#1775000
0"
17
b0 6
b101001101000010111 ;
b0 :
b1001101110101001 9
1%
#1780000
0%
0+
#1785000
b1 6
b110110001100100110 ;
b110110010001010111 :
1%
#1790000
0%
#1795000
b10 6
b111101100111010111 ;
b110001011010000011 :
b100110111010100 9
1%
#1800000
0%
#1805000
b11 6
b1100010001101 ;
b110000001100001110 :
b1001101110100 9
1%
#1810000
0%
#1815000
b100 6
b111111100010111100 ;
b110000010101111100 :
b11001100010011 9
1%
#1820000
0%
#1825000
b101 6
b100010110110 ;
b110000001001001011 :
b10001101101010 9
1%
#1830000
0%
#1835000
b110 6
b10111001 ;
b110000001101100110 :
b10101101011000 9
1%
#1840000
0%
#1845000
b111 6
b111111110010111010 ;
b110000010000010011 :
b10111101001011 9
1%
#1850000
0%
#1855000
b1000 6
b111111111010111010 ;
b110000001110110101 :
b10110101010011 9
1%
#1860000
0%
#1865000
b1001 6
b111111111110111010 ;
b110000001110001000 :
b10110001010110 9
1%
#1870000
0%
#1875000
b1010 6
b111010 ;
b110000001101110010 :
b10101111010111 9
1%
#1880000
0%
#1885000
b1011 6
b111111111111111010 ;
b110000001101111100 :
b10110000010111 9
1%
#1890000
0%
#1895000
b1100 6
b11010 ;
b110000001101110111 :
b10101111110111 9
1%
#1900000
0%
#1905000
b1101 6
b1010 ;
b110000001101111001 :
b10110000000111 9
1%
#1910000
0%
#1915000
b1110 6
b10 ;
b110000001101111010 :
b10110000001111 9
1%
#1920000
0%
#1925000
07
1"
b110000001101111010 !
b110000001101111010 8
b10110000001111 #
b10110000001111 5
1%
#1930000
1+
b110000010010001000 (
b10111111110010 '
r-0.9823030783818857 /
r0.1872983240754466 -
r-1.38238525390625 .
b101001111000011100 $
b101001111000011100 4
b11111111111111101001111000011100 ,
b1010 *
b111 &
b111 3
b110000001101111010 1
b110000001111001111 2
0%
#1935000
0"
17
b0 6
b101001111000011100 ;
b0 :
b1001101110101001 9
1%
#1940000
0%
0+
#1945000
b1 6
b110110011100101011 ;
b110110010001010111 :
1%
